pyreinst/__init__.py
pyreinst-0.0.1.dist-info/METADATA
pyreinst-0.0.1.dist-info/WHEEL
pyreinst-0.0.1.dist-info/entry_points.txt
pyreinst-0.0.1.dist-info/top_level.txt
pyreinst-0.0.1.dist-info/RECORD
