Metadata-Version: 2.1
Name: pyreinst
Version: 0.0.1
Summary: Reinstall script
Home-page: https://github.com/mugiseyebrows/pyreinst
Author: Stanislav Doronin
Author-email: mugisbrows@gmail.com
